covidbeta.py
covidbeta-0.0.1.dist-info/METADATA
covidbeta-0.0.1.dist-info/WHEEL
covidbeta-0.0.1.dist-info/entry_points.txt
covidbeta-0.0.1.dist-info/top_level.txt
covidbeta-0.0.1.dist-info/RECORD
