Metadata-Version: 2.1
Name: covidbeta
Version: 0.0.1
Summary: A package for visualize expected number of new infections and new deaths by country due to Covid-19.
Home-page: https://github.com/yugo-Ishihara/covidcasev
Author: Yugo Ishihara
Author-email: s2022041@stu.musashino-u.ac.jp
License: UNKNOWN
Project-URL: covidbeta, https://github.com/yugo-Ishihara/covidcasev
Platform: UNKNOWN
Classifier: Programming Language :: Python :: 3
Classifier: License :: OSI Approved :: MIT License
Classifier: Operating System :: OS Independent
Requires-Python: >=3.8
